odoo8_addon_l10n_es_aeat_mod349-8.0.2.2.0.99.dev38-py3.8-nspkg.pth
odoo_addons/l10n_es_aeat_mod349/README.rst
odoo_addons/l10n_es_aeat_mod349/__init__.py
odoo_addons/l10n_es_aeat_mod349/__openerp__.py
odoo_addons/l10n_es_aeat_mod349/data/assign_invoices_op_keys.xml
odoo_addons/l10n_es_aeat_mod349/docs/BOE-A-2010-5098.pdf
odoo_addons/l10n_es_aeat_mod349/docs/dr349_2009.pdf
odoo_addons/l10n_es_aeat_mod349/i18n/bg.po
odoo_addons/l10n_es_aeat_mod349/i18n/ca.po
odoo_addons/l10n_es_aeat_mod349/i18n/ca_ES.po
odoo_addons/l10n_es_aeat_mod349/i18n/cs.po
odoo_addons/l10n_es_aeat_mod349/i18n/en_US.po
odoo_addons/l10n_es_aeat_mod349/i18n/es.po
odoo_addons/l10n_es_aeat_mod349/i18n/es_CO.po
odoo_addons/l10n_es_aeat_mod349/i18n/es_CR.po
odoo_addons/l10n_es_aeat_mod349/i18n/eu.po
odoo_addons/l10n_es_aeat_mod349/i18n/fr.po
odoo_addons/l10n_es_aeat_mod349/i18n/gl.po
odoo_addons/l10n_es_aeat_mod349/i18n/hr.po
odoo_addons/l10n_es_aeat_mod349/i18n/l10n_es_aeat_mod349.pot
odoo_addons/l10n_es_aeat_mod349/i18n/nl.po
odoo_addons/l10n_es_aeat_mod349/i18n/pl.po
odoo_addons/l10n_es_aeat_mod349/i18n/pt.po
odoo_addons/l10n_es_aeat_mod349/i18n/pt_BR.po
odoo_addons/l10n_es_aeat_mod349/i18n/ru.po
odoo_addons/l10n_es_aeat_mod349/i18n/sl.po
odoo_addons/l10n_es_aeat_mod349/i18n/sv.po
odoo_addons/l10n_es_aeat_mod349/i18n/tr.po
odoo_addons/l10n_es_aeat_mod349/i18n/vi.po
odoo_addons/l10n_es_aeat_mod349/models/__init__.py
odoo_addons/l10n_es_aeat_mod349/models/account_fiscal_position.py
odoo_addons/l10n_es_aeat_mod349/models/account_invoice.py
odoo_addons/l10n_es_aeat_mod349/models/mod349.py
odoo_addons/l10n_es_aeat_mod349/report/mod349_report.rml
odoo_addons/l10n_es_aeat_mod349/report/mod349_report.xml
odoo_addons/l10n_es_aeat_mod349/security/ir.model.access.csv
odoo_addons/l10n_es_aeat_mod349/security/mod_349_security.xml
odoo_addons/l10n_es_aeat_mod349/static/description/icon.png
odoo_addons/l10n_es_aeat_mod349/static/description/icon_source.svg
odoo8_addon_l10n_es_aeat_mod349-8.0.2.2.0.99.dev38.dist-info/METADATA
odoo8_addon_l10n_es_aeat_mod349-8.0.2.2.0.99.dev38.dist-info/WHEEL
odoo8_addon_l10n_es_aeat_mod349-8.0.2.2.0.99.dev38.dist-info/namespace_packages.txt
odoo8_addon_l10n_es_aeat_mod349-8.0.2.2.0.99.dev38.dist-info/top_level.txt
odoo8_addon_l10n_es_aeat_mod349-8.0.2.2.0.99.dev38.dist-info/RECORD
