Metadata-Version: 2.1
Name: odoo8-addon-l10n-es-aeat-mod349
Version: 8.0.2.2.0.99.dev38
Summary: Modelo 349 AEAT
Home-page: https://github.com/OCA/l10n-spain
Author: Pexego, Top Consultant, Serv. Tecnol. Avanzados - Pedro M. Baeza, Antiun Ingeniería S.L.,Odoo Community Association (OCA)
Author-email: support@odoo-community.org
License: AGPL-3
Platform: UNKNOWN
Classifier: Programming Language :: Python
Classifier: Framework :: Odoo
Classifier: Framework :: Odoo :: 8.0
Classifier: License :: OSI Approved :: GNU Affero General Public License v3
Requires-Python: ~=2.7
Requires-Dist: odoo8-addon-account-invoice-currency
Requires-Dist: odoo8-addon-account-refund-original
Requires-Dist: odoo8-addon-l10n-es-aeat
Requires-Dist: odoo (<9.0a,>=8.0a)
